notebooklm2ppt/__init__.py
notebooklm2ppt/__main__.py
notebooklm2ppt/cli.py
notebooklm2ppt/config_defaults.py
notebooklm2ppt/gui.py
notebooklm2ppt/pdf2png.py
notebooklm2ppt/i18n/__init__.py
notebooklm2ppt/i18n/en.py
notebooklm2ppt/i18n/zh_cn.py
notebooklm2ppt/utils/__init__.py
notebooklm2ppt/utils/coordinate_utils.py
notebooklm2ppt/utils/edge_diversity.py
notebooklm2ppt/utils/image_inpainter.py
notebooklm2ppt/utils/image_viewer.py
notebooklm2ppt/utils/inpaint_methods.py
notebooklm2ppt/utils/ppt_combiner.py
notebooklm2ppt/utils/ppt_refiner.py
notebooklm2ppt/utils/process_checker.py
notebooklm2ppt/utils/screenshot_automation.py
notebooklm2ppt-0.7.2.dist-info/METADATA
notebooklm2ppt-0.7.2.dist-info/WHEEL
notebooklm2ppt-0.7.2.dist-info/entry_points.txt
notebooklm2ppt-0.7.2.dist-info/licenses/LICENSE
notebooklm2ppt-0.7.2.dist-info/RECORD
