Metadata-Version: 2.4
Name: notebooklm2ppt
Version: 0.7.2
Summary: 将 PDF 转换为可编辑 PowerPoint 演示文稿的工具
Project-URL: Homepage, https://github.com/elliottzheng/NotebookLM2PPT
Project-URL: Repository, https://github.com/elliottzheng/NotebookLM2PPT.git
Project-URL: Issues, https://github.com/elliottzheng/NotebookLM2PPT/issues
Author-email: Elliott Zheng <elliott.zheng@foxmail.com>
License: MIT
License-File: LICENSE
Requires-Python: >=3.8
Requires-Dist: numpy
Requires-Dist: pillow
Requires-Dist: pymupdf
Requires-Dist: python-pptx
Requires-Dist: pywin32; sys_platform == 'win32'
Requires-Dist: pywinauto; sys_platform == 'win32'
Requires-Dist: requests
Requires-Dist: scikit-image
Requires-Dist: spire-presentation
Requires-Dist: windnd; sys_platform == 'win32'
